schupy/__init__.py
schupy/schupy.py
schupy-1.0.7.dist-info/LICENSE
schupy-1.0.7.dist-info/METADATA
schupy-1.0.7.dist-info/WHEEL
schupy-1.0.7.dist-info/top_level.txt
schupy-1.0.7.dist-info/RECORD
