Metadata-Version: 2.1
Name: schupy
Version: 1.0.7
Summary: A python package for modeling Schumann resonances
Home-page: https://github.com/dalyagergely/schupy
Author: Gergely Dálya, Tamás Bozóki, Kornél Kapás, János Takátsy, Ernő Prácser, Gabriella Sátori
Author-email: dalyag@caesar.elte.hu
License: UNKNOWN
Platform: UNKNOWN
Classifier: Programming Language :: Python :: 3
Classifier: License :: OSI Approved :: MIT License
Classifier: Operating System :: OS Independent
